Metadata-Version: 2.1
Name: shaxrux-pip-test
Version: 0.1
Summary: Shaxrux`s testing pip project
Home-page: UNKNOWN
Author-email: tleubaevshaxrux@outlook.com
License: UNKNOWN
Platform: UNKNOWN
